headpose/__init__.py
headpose/dataset.py
headpose/detect.py
headpose/haarcascade_frontalface_default.xml
headpose/train_network.py
headpose/tests/__init__.py
headpose/tests/test_headpose.py
headpose-1.1.8.dist-info/METADATA
headpose-1.1.8.dist-info/WHEEL
headpose-1.1.8.dist-info/top_level.txt
headpose-1.1.8.dist-info/RECORD
