Metadata-Version: 2.1
Name: headpose
Version: 1.1.8
Summary: estimate the pose of the head based on an image.
Home-page: https://github.com/OleBialas/headpose.git
Author: Ole Bialas
Author-email: bialas@cbs.mpg.de
License: MIT
Platform: UNKNOWN
Requires-Python: >=3.6
Requires-Dist: opencv-python
Requires-Dist: numpy
Requires-Dist: requests
Requires-Dist: torch
Requires-Dist: torchvision
